pyannote.metrics-3.2.1-py3.10-nspkg.pth
pyannote/metrics/__init__.py
pyannote/metrics/_version.py
pyannote/metrics/base.py
pyannote/metrics/binary_classification.py
pyannote/metrics/cli.py
pyannote/metrics/detection.py
pyannote/metrics/diarization.py
pyannote/metrics/identification.py
pyannote/metrics/matcher.py
pyannote/metrics/segmentation.py
pyannote/metrics/spotting.py
pyannote/metrics/types.py
pyannote/metrics/utils.py
pyannote/metrics/errors/__init__.py
pyannote/metrics/errors/identification.py
pyannote/metrics/errors/segmentation.py
pyannote/metrics/plot/__init__.py
pyannote/metrics/plot/binary_classification.py
pyannote.metrics-3.2.1.dist-info/LICENSE
pyannote.metrics-3.2.1.dist-info/METADATA
pyannote.metrics-3.2.1.dist-info/WHEEL
pyannote.metrics-3.2.1.dist-info/entry_points.txt
pyannote.metrics-3.2.1.dist-info/namespace_packages.txt
pyannote.metrics-3.2.1.dist-info/top_level.txt
pyannote.metrics-3.2.1.dist-info/RECORD
