Metadata-Version: 2.1
Name: pyannote.metrics
Version: 3.2.1
Summary: a toolkit for reproducible evaluation, diagnostic, and error analysis of speaker diarization systems
Home-page: https://pyannote.github.io/pyannote-metrics
Author: Herve Bredin
Author-email: bredin@limsi.fr
License: UNKNOWN
Platform: UNKNOWN
Classifier: Development Status :: 4 - Beta
Classifier: Intended Audience :: Science/Research
Classifier: License :: OSI Approved :: MIT License
Classifier: Natural Language :: English
Classifier: Programming Language :: Python :: 3
Classifier: Programming Language :: Python :: 3.7
Classifier: Programming Language :: Python :: 3.8
Classifier: Topic :: Scientific/Engineering
Provides-Extra: tests
Provides-Extra: docs
License-File: LICENSE
